ponyo/helper_vae.py
ponyo/simulate_expression_data.py
ponyo/train_vae_modules.py
ponyo/utils.py
ponyo/vae.py
ponyo-0.7.1.dist-info/LICENSE
ponyo-0.7.1.dist-info/METADATA
ponyo-0.7.1.dist-info/WHEEL
ponyo-0.7.1.dist-info/top_level.txt
ponyo-0.7.1.dist-info/RECORD
