Metadata-Version: 2.1
Name: ponyo
Version: 0.7.1
Summary: Install functions to simulate gene expression compendia
Home-page: https://github.com/greenelab/ponyo
Author: Alexandra Lee
Author-email: alexjlee.21@gmail.com
License: BSD 3-Clause
Platform: UNKNOWN
Requires-Python: >=3.5, <3.8
Requires-Dist: pandas
Requires-Dist: numpy
Requires-Dist: keras (==2.3.1)
Requires-Dist: tensorflow (==1.15.4)
Requires-Dist: scikit-learn
Requires-Dist: h5py (<3)
Provides-Extra: test
Requires-Dist: pytest ; extra == 'test'
Requires-Dist: nbval ; extra == 'test'
Requires-Dist: umap-learn ; extra == 'test'
Requires-Dist: plotnine ; extra == 'test'
Requires-Dist: coverage (<5.0) ; extra == 'test'
Requires-Dist: pytest-cov ; extra == 'test'
Requires-Dist: coveralls (==2.2.0) ; extra == 'test'
